[
    {
        "id": 13,
        "taskName": "23",
        "bakingBatch": "20250211110835",
        "createTime": "2025-02-11 11:08:35",
        "finishTime": "2025-02-13 23:59",
        "number": "23",
        "numberOfBeans": "23",
        "bakingStatue": 1,
        "bakingDeviceId": 2,
        "taskId": "868306535330077095",
        "stage1": [
            0,
            0,
            0,
            0
        ],
        "stage2": [
            0,
            0,
            0,
            0
        ],
        "stage3": [
            0,
            0,
            0,
            0
        ],
        "stage4": [
            0,
            0,
            0,
            0
        ],
        "stage5": [
            0,
            0,
            0,
            0
        ],
        "stage6": [
            0,
            0,
            0,
            0
        ]
    },
    {
        "id": 14,
        "taskName": "233",
        "bakingBatch": "20250211110848",
        "createTime": "2025-02-11 11:08:48",
        "finishTime": "2025-02-12 23:59",
        "number": "3",
        "numberOfBeans": "3",
        "bakingStatue": 1,
        "bakingDeviceId": 2,
        "taskId": "162099973611217716",
        "stage1": [
            0,
            0,
            0,
            0
        ],
        "stage2": [
            0,
            0,
            0,
            0
        ],
        "stage3": [
            0,
            0,
            0,
            0
        ],
        "stage4": [
            0,
            0,
            0,
            0
        ],
        "stage5": [
            0,
            0,
            0,
            0
        ],
        "stage6": [
            0,
            0,
            0,
            0
        ]
    },
    {
        "id": 15,
        "taskName": "实时5",
        "bakingBatch": "20250211164146",
        "createTime": "2025-02-11 16:41:46",
        "finishTime": "2025-02-08 23:59",
        "number": "5",
        "numberOfBeans": "5",
        "bakingStatue": 1,
        "bakingDeviceId": 2,
        "taskId": "099685851514574000",
        "stage1": [
            9,
            9,
            9,
            9
        ],
        "stage2": [
            0,
            0,
            0,
            0
        ],
        "stage3": [
            0,
            0,
            0,
            0
        ],
        "stage4": [
            0,
            0,
            0,
            0
        ],
        "stage5": [
            0,
            0,
            0,
            0
        ],
        "stage6": [
            0,
            0,
            0,
            0
        ]
    },
    {
        "id": 17,
        "taskName": "56",
        "bakingBatch": "20250213092320",
        "createTime": "2025-02-13 09:23:20",
        "finishTime": "2025-02-13 23:59",
        "number": "5",
        "numberOfBeans": "5",
        "bakingStatue": 1,
        "bakingDeviceId": 2,
        "taskId": "959668182434962042",
        "stage1": [
            0,
            0,
            0,
            0
        ],
        "stage2": [
            0,
            0,
            0,
            0
        ],
        "stage3": [
            0,
            0,
            0,
            0
        ],
        "stage4": [
            0,
            0,
            0,
            0
        ],
        "stage5": [
            0,
            0,
            0,
            0
        ],
        "stage6": [
            0,
            0,
            0,
            0
        ]
    },
    {
        "id": 18,
        "taskName": "777",
        "bakingBatch": "20250213092424",
        "createTime": "2025-02-13 09:24:24",
        "finishTime": "2025-02-13 23:59",
        "number": "7",
        "numberOfBeans": "7",
        "bakingStatue": 1,
        "bakingDeviceId": 2,
        "taskId": "340941594873358055",
        "stage1": [
            0,
            0,
            0,
            0
        ],
        "stage2": [
            0,
            0,
            0,
            0
        ],
        "stage3": [
            0,
            0,
            0,
            0
        ],
        "stage4": [
            0,
            0,
            0,
            0
        ],
        "stage5": [
            0,
            0,
            0,
            0
        ],
        "stage6": [
            0,
            0,
            0,
            0
        ]
    }
]